saheffects/__init__.py
saheffects/saheffects.py
saheffects-0.1.1.dist-info/AUTHORS.rst
saheffects-0.1.1.dist-info/LICENSE
saheffects-0.1.1.dist-info/METADATA
saheffects-0.1.1.dist-info/WHEEL
saheffects-0.1.1.dist-info/top_level.txt
saheffects-0.1.1.dist-info/RECORD
