Metadata-Version: 2.1
Name: saheffects
Version: 0.1.1
Summary: saheffects  is a Python package for applying various image filters to images.
Home-page: https://github.com/SahSofts/saheffects
Author: SahSofts
Author-email: sahsofts97@gmail.com
License: MIT license
Keywords: saheffects
Classifier: Development Status :: 2 - Pre-Alpha
Classifier: Intended Audience :: Developers
Classifier: License :: OSI Approved :: MIT License
Classifier: Natural Language :: English
Classifier: Programming Language :: Python :: 3
Classifier: Programming Language :: Python :: 3.6
Classifier: Programming Language :: Python :: 3.7
Classifier: Programming Language :: Python :: 3.8
Requires-Python: >=3.6
License-File: LICENSE
License-File: AUTHORS.rst
